tgbotstat/__init__.py
tgbotstat/tgbotstat.py
tgbotstat-1.0.1.dist-info/LICENSE
tgbotstat-1.0.1.dist-info/METADATA
tgbotstat-1.0.1.dist-info/WHEEL
tgbotstat-1.0.1.dist-info/top_level.txt
tgbotstat-1.0.1.dist-info/RECORD
