Metadata-Version: 2.1
Name: tgbotstat
Version: 1.0.1
Summary: Un outil pour suivre les statistiques d'utilisation des commandes d'un bot Telegram.
Home-page: https://github.com/codingtuto/tgbotstat
Author: Coding Team
Author-email: codingteam@telegmail.com
Classifier: Programming Language :: Python :: 3
Classifier: License :: OSI Approved :: MIT License
Classifier: Operating System :: OS Independent
License-File: LICENSE
